RobotCode/__init__.py
pikitlib/__init__.py
pikitlib/analoginput.py
pikitlib/buffer.py
pikitlib/buzzer.py
pikitlib/differentialdrive.py
pikitlib/iterativerobotbase.py
pikitlib/pca_motor.py
pikitlib/robotdrivebase.py
pikitlib/run.py
pikitlib/speedcontroller.py
pikitlib/speedcontrollergroup.py
pikitlib/timedrobot.py
pikitlib/timer.py
pikitlib/xboxconfig.py
pikitlib/xboxcontroller.py
tests/__init__.py
tests/test_drivetrain.py
pikitlib-0.0.12.dist-info/METADATA
pikitlib-0.0.12.dist-info/WHEEL
pikitlib-0.0.12.dist-info/top_level.txt
pikitlib-0.0.12.dist-info/RECORD
