Metadata-Version: 2.1
Name: pikitlib
Version: 0.0.12
Summary: WPILIb-equivilent for 1076 robot kits
Home-page: UNKNOWN
Author: 1076
Author-email: UNKNOWN
License: None
Platform: UNKNOWN
Requires-Dist: pynetworktables
Requires-Dist: pygame
